pygments_restrict/__init__.py
pygments_restrict/lexers.py
pygments_restrict-0.1.5.dist-info/METADATA
pygments_restrict-0.1.5.dist-info/WHEEL
pygments_restrict-0.1.5.dist-info/entry_points.txt
pygments_restrict-0.1.5.dist-info/RECORD
